<step-type name="Delete Node">
  <description> This will be used to delete a node.</description>
  <properties>
    <property name="name" required="true">  
      <property-ui type="textBox" label="Enter node name" description="Deletes the given node."/>
    </property>           
  </properties>
  <post-processing><![CDATA[
      if (properties.get("exitCode") != 0) {
          properties.put("Status", "Failure");
      }
      else {
          properties.put("Status", "Success");
      }
   ]]></post-processing>

  <command program="${GROOVY_HOME}/bin/groovy">
    <arg file="deleteNode.groovy"/>
    <arg file="${PLUGIN_INPUT_PROPS}"/>
    <arg file="${PLUGIN_OUTPUT_PROPS}"/>
  </command>
  
</step-type>
